setup.cfg
setup.py
src/modelchemy/__init__.py
src/modelchemy/app.py
src/modelchemy/init.py
src/modelchemy/mappings.py
src/modelchemy/middleware.py
src/modelchemy/registry.py
src/modelchemy/requests.py
src/modelchemy/router.py
src/modelchemy/selector.py
src/modelchemy/shims.py
src/modelchemy/utilities.py
src/modelchemy/values.py
src/modelchemy.egg-info/PKG-INFO
src/modelchemy.egg-info/SOURCES.txt
src/modelchemy.egg-info/dependency_links.txt
src/modelchemy.egg-info/requires.txt
src/modelchemy.egg-info/top_level.txt
src/modelchemy/management/__init__.py
src/modelchemy/management/commands/__init__.py
src/modelchemy/management/commands/modelchemy.py
src/modelchemy/management/subcommands/__init__.py
src/modelchemy/management/subcommands/base.py
src/modelchemy/management/subcommands/create_all.py
src/modelchemy/management/subcommands/drop_all.py